{
  "$schema": "https://turbo.build/schema.json",
  "ui": "tui",
  "tasks": {
    "build": {
      "dependsOn": ["^build"],
      "outputs": ["dist/**", ".next/**", "build/**", ".expo/**"]
    },
    "start": {
      "cache": false,
      "persistent": true
    },
    "dev": {
      "cache": false,
      "persistent": true
    },
    "lint": {
      "dependsOn": ["^lint"]
    },
    "typecheck": {
      "dependsOn": ["^typecheck"]
    },
    "test": {
      "dependsOn": ["^build"],
      "outputs": ["coverage/**"]
    },
    "clean": {
      "cache": false
    }
  }
}